nskipgrams.py
nskipgrams-0.5.0.dist-info/LICENSE.txt
nskipgrams-0.5.0.dist-info/METADATA
nskipgrams-0.5.0.dist-info/WHEEL
nskipgrams-0.5.0.dist-info/top_level.txt
nskipgrams-0.5.0.dist-info/RECORD
