Metadata-Version: 2.1
Name: nskipgrams
Version: 0.5.0
Summary: A lightweight Python package to work with ngrams and skipgrams
Author-email: "Jackson L. Lee" <jacksonlunlee@gmail.com>
License: MIT License
Project-URL: Source, https://github.com/jacksonllee/nskipgrams
Keywords: computational linguistics,natural language processing,NLP,linguistics,language,ngrams,skipgrams
Classifier: Development Status :: 4 - Beta
Classifier: Intended Audience :: Developers
Classifier: Intended Audience :: Education
Classifier: Intended Audience :: Information Technology
Classifier: Intended Audience :: Science/Research
Classifier: License :: OSI Approved :: MIT License
Classifier: Operating System :: OS Independent
Classifier: Programming Language :: Python :: 3
Classifier: Programming Language :: Python :: 3 :: Only
Classifier: Programming Language :: Python :: 3.8
Classifier: Programming Language :: Python :: 3.9
Classifier: Programming Language :: Python :: 3.10
Classifier: Programming Language :: Python :: 3.11
Classifier: Topic :: Scientific/Engineering
Classifier: Topic :: Scientific/Engineering :: Artificial Intelligence
Classifier: Topic :: Scientific/Engineering :: Human Machine Interfaces
Classifier: Topic :: Scientific/Engineering :: Information Analysis
Classifier: Topic :: Text Processing
Classifier: Topic :: Text Processing :: General
Classifier: Topic :: Text Processing :: Indexing
Classifier: Topic :: Text Processing :: Linguistic
Requires-Python: >=3.8
License-File: LICENSE.txt
Provides-Extra: dev
Requires-Dist: black (==23.1.0) ; extra == 'dev'
Requires-Dist: flake8 (==6.0.0) ; extra == 'dev'
Requires-Dist: pytest (==7.2.1) ; extra == 'dev'
Requires-Dist: build (==0.10.0) ; extra == 'dev'
Requires-Dist: twine (==4.0.2) ; extra == 'dev'
